dm_client/__init__.py
dm_client/transaction/__init__.py
dm_client/transaction/apps.py
dm_client/transaction/constants.py
dm_client/transaction/exceptions.py
dm_client/transaction/service.py
dm_client/transaction/utils.py
dm_client/transaction/tests/__init__.py
dm_client_transaction-1.0.1.dist-info/licenses/LICENSE
dm_client_transaction-1.0.1.dist-info/METADATA
dm_client_transaction-1.0.1.dist-info/WHEEL
dm_client_transaction-1.0.1.dist-info/top_level.txt
dm_client_transaction-1.0.1.dist-info/RECORD
